{
	"schemaVersion": 1,
	"id": "better-particles",
	"version": "${version}",
	"name": "Better Particles",
	"description": "这是一个供玩家自由创建粒子效果的工具",
	"authors": [
		"Vanilla"
	],
	"contact": {
		"sources": "https://github.com/Vanil1a-Chocolate/better-particles-template-1.21"
	},
	"license": "CC0-1.0",
	"icon": "assets/better-particles/icon.png",
	"environment": "*",
	"entrypoints": {
		"main": [
			"com.vanilla.BetterParticles"
		],
		"fabric-datagen": [
			"com.vanilla.BetterParticlesDataGenerator"
		],
		"client": [
			"com.vanilla.BetterParticlesClient"
		]
	},
	"mixins": [
		"better-particles.mixins.json"
	],
	"depends": {
		"fabricloader": ">=0.17.2",
		"minecraft": "~1.21",
		"java": ">=21",
		"fabric-api": "*"
	},
	"suggests": {
		"another-mod": "*"
	}
}